shinkuro/__init__.py
shinkuro/formatters.py
shinkuro/interfaces.py
shinkuro/loader.py
shinkuro/main.py
shinkuro/model.py
shinkuro/file/__init__.py
shinkuro/file/scan.py
shinkuro/prompts/__init__.py
shinkuro/prompts/markdown.py
shinkuro/remote/__init__.py
shinkuro/remote/git.py
shinkuro-0.3.5.dist-info/METADATA
shinkuro-0.3.5.dist-info/WHEEL
shinkuro-0.3.5.dist-info/entry_points.txt
shinkuro-0.3.5.dist-info/licenses/LICENSE
shinkuro-0.3.5.dist-info/RECORD
