Metadata-Version: 2.4
Name: shinkuro
Version: 0.3.5
Summary: Universal prompt loader MCP server
Project-URL: Homepage, https://github.com/DiscreteTom/shinkuro
Project-URL: Repository, https://github.com/DiscreteTom/shinkuro
Project-URL: Issues, https://github.com/DiscreteTom/shinkuro/issues
Author-email: DiscreteTom <discrete_tom@outlook.com>
License: MIT
License-File: LICENSE
Keywords: mcp,model-context-protocol,prompt
Classifier: Intended Audience :: Developers
Classifier: License :: OSI Approved :: MIT License
Classifier: Programming Language :: Python :: 3
Classifier: Programming Language :: Python :: 3.10
Classifier: Programming Language :: Python :: 3.11
Classifier: Programming Language :: Python :: 3.12
Classifier: Programming Language :: Python :: 3.13
Classifier: Topic :: Software Development :: Libraries :: Python Modules
Requires-Python: >=3.10
Requires-Dist: fastmcp>=2.12.4
Requires-Dist: gitpython>=3.1.0
Requires-Dist: giturlparse>=0.12.0
Requires-Dist: python-frontmatter>=1.1.0
Requires-Dist: typer>=0.20.0
